yandex_market_api/__init__.py
yandex_market_api/client.py
yandex_market_api/config.py
yandex_market_api/resources/base.py
yandex_market_api/resources/businesses.py
yandex_market_api/resources/campaigns.py
yandex_market_api/resources/categories.py
yandex_market_api/resources/offers.py
yandex_market_api/resources/prices.py
yandex_market_api/resources/recommendations.py
yandex_market_api/resources/reports.py
yandex_market_api/resources/tariffs.py
yandex_market_api-0.1.0.dist-info/METADATA
yandex_market_api-0.1.0.dist-info/WHEEL
yandex_market_api-0.1.0.dist-info/RECORD
