Metadata-Version: 2.4
Name: yandex-market-api
Version: 0.1.0
Summary: Async Python SDK for Yandex Market Partner API
Author: argoarsiks
Author-email: argoars@icloud.com
Requires-Python: >=3.10
Classifier: Programming Language :: Python :: 3
Classifier: Programming Language :: Python :: 3.10
Classifier: Programming Language :: Python :: 3.11
Classifier: Programming Language :: Python :: 3.12
Classifier: Programming Language :: Python :: 3.13
Classifier: Programming Language :: Python :: 3.14
Requires-Dist: httpx (>=0.28.1,<0.29.0)
Requires-Dist: pydantic (>=2.12.5,<3.0.0)
Requires-Dist: pydantic-settings (>=2.12.0,<3.0.0)
Project-URL: Repository, https://github.com/argoarsiks/yandex-market-api
